odoo/addons/stock_available_global/README.rst
odoo/addons/stock_available_global/__init__.py
odoo/addons/stock_available_global/__manifest__.py
odoo/addons/stock_available_global/i18n/es.po
odoo/addons/stock_available_global/i18n/stock_available_global.pot
odoo/addons/stock_available_global/models/__init__.py
odoo/addons/stock_available_global/models/product_product.py
odoo/addons/stock_available_global/models/product_stock_available_mixin.py
odoo/addons/stock_available_global/models/product_template.py
odoo/addons/stock_available_global/models/sale_stock.py
odoo/addons/stock_available_global/static/description/icon.png
odoo/addons/stock_available_global/views/product_product_view.xml
odoo/addons/stock_available_global/views/product_template_view.xml
odoo11_addon_stock_available_global-11.0.1.0.1.dist-info/METADATA
odoo11_addon_stock_available_global-11.0.1.0.1.dist-info/WHEEL
odoo11_addon_stock_available_global-11.0.1.0.1.dist-info/top_level.txt
odoo11_addon_stock_available_global-11.0.1.0.1.dist-info/RECORD
